README.md
setup.py
BeraChainTools/__init__.py
BeraChainTools/bera_tools.py
BeraChainTools.egg-info/PKG-INFO
BeraChainTools.egg-info/SOURCES.txt
BeraChainTools.egg-info/dependency_links.txt
BeraChainTools.egg-info/requires.txt
BeraChainTools.egg-info/top_level.txt