Metadata-Version: 2.1
Name: BeraChainTools
Version: 0.0.1
Home-page: https://github.com/ymmmmmmmm/BeraChainTools
Author: ym
Author-email: 49154181@qq.com
License: MIT Licence
Keywords: pip,BeraChainTools,BeraChain
Platform: any
